LAB2/problem3_vending/vending_mealy.v

module vending_mealy(
    input  wire       clk,
    input  wire       rst,       
    input  wire [1:0] coin,      
    output reg        dispense,  
    output reg        chg5      
);

    
    localparam S0  = 2'd0; 
    localparam S5  = 2'd1; 
    localparam S10 = 2'd2; 
    localparam S15 = 2'd3;

    reg [1:0] state, next_state;

    
    wire coin5  = (coin == 2'b01);
    wire coin10 = (coin == 2'b10);
    wire idle   = (coin == 2'b00);
    always @(*) begin
        dispense   = 1'b0;
        chg5       = 1'b0;

        next_state = state;

        case (state)
            S0: begin
                if (coin5)       next_state = S5;
                else if (coin10) next_state = S10;
                else             next_state = S0; 
            end

            S5: begin
                if (coin5)       next_state = S10;
                else if (coin10) next_state = S15;
                else             next_state = S5;
            end

            S10: begin
                if (coin10) begin
                    dispense   = 1'b1; 
                    next_state = S0;
                end else if (coin5) begin
                    next_state = S15;
                end else begin
                    next_state = S10;
                end
            end

            S15: begin
                if (coin5) begin
                    dispense   = 1'b1;
                    next_state = S0;
                end else if (coin10) begin
                    dispense   = 1'b1;
                    chg5       = 1'b1;
                    next_state = S0;
                end else begin
                    next_state = S15;
                end
            end

            default: next_state = S0;
        endcase
    end

    always @(posedge clk) begin
        if (rst) begin
            state <= S0;
        end else begin
            state <= next_state;
        end
    end

endmodule

LAB2/problem3_vending/tb_vending_mealy.v

`timescale 1ns/1ps

module tb_vending_mealy;
    reg        clk;
    reg        rst;
    reg [1:0]  coin;
    wire       dispense;
    wire       chg5;


    vending_mealy dut(
        .clk(clk), .rst(rst), .coin(coin),
        .dispense(dispense), .chg5(chg5)
    );


    initial begin
        clk = 0;
        forever #5 clk = ~clk;
    end

    task put5;  begin coin = 2'b01; @(posedge clk); coin = 2'b00; end endtask
    task put10; begin coin = 2'b10; @(posedge clk); coin = 2'b00; end endtask
    task idle1; begin coin = 2'b00; @(posedge clk); end endtask


    always @(posedge clk) begin
        if (dispense || chg5)
            $display("%0t ns: dispense=%b chg5=%b (coin=%b)",
                     $time, dispense, chg5, coin);
    end

    initial begin
        $dumpfile("dump.vcd");
        $dumpvars(0, tb_vending_mealy);


        coin = 2'b00;
        rst  = 1;
        repeat (3) @(posedge clk);
        rst  = 0;


        idle1; put10; idle1; put10; idle1;


        idle1; put5; idle1; put5; idle1; put10; idle1;


        idle1; put10; idle1; put5; idle1; put10; idle1;

        repeat (5) @(posedge clk);
        $display("TB done.");
        $finish;
    end
endmodule

LAB2/problem3_vending/dump.vcd
$date
	Mon Aug 18 13:07:39 2025
$end
$version
	Icarus Verilog
$end
$timescale
	1ps
$end
$scope module tb_vending_mealy $end
$var wire 1 ! dispense $end
$var wire 1 " chg5 $end
$var reg 1 # clk $end
$var reg 2 $ coin [1:0] $end
$var reg 1 % rst $end
$scope module dut $end
$var wire 1 # clk $end
$var wire 2 & coin [1:0] $end
$var wire 1 % rst $end
$var wire 1 ' idle $end
$var wire 1 ( coin5 $end
$var wire 1 ) coin10 $end
$var reg 1 " chg5 $end
$var reg 1 ! dispense $end
$var reg 2 * next_state [1:0] $end
$var reg 2 + state [1:0] $end
$upscope $end
$scope task idle1 $end
$upscope $end
$scope task put10 $end
$upscope $end
$scope task put5 $end
$upscope $end
$upscope $end
$enddefinitions $end
#0
$dumpvars
bx +
b0 *
0)
0(
1'
b0 &
1%
b0 $
0#
0"
0!
$end
#5000
b0 +
1#
#10000
0#
#15000
1#
#20000
0#
#25000
0%
1#
#30000
0#
#35000
b10 *
1)
0'
b10 $
b10 &
1#
#40000
0#
#45000
b10 +
b10 *
0)
1'
b0 $
b0 &
1#
#50000
0#
#55000
b0 *
1!
1)
0'
b10 $
b10 &
1#
#60000
0#
#65000
b0 +
b0 *
0!
0)
1'
b0 $
b0 &
1#
#70000
0#
#75000
1#
#80000
0#
#85000
b1 *
1(
0'
b1 $
b1 &
1#
#90000
0#
#95000
b1 +
b1 *
0(
1'
b0 $
b0 &
1#
#100000
0#
#105000
b10 *
1(
0'
b1 $
b1 &
1#
#110000
0#
#115000
b10 +
b10 *
0(
1'
b0 $
b0 &
1#
#120000
0#
#125000
b0 *
1!
1)
0'
b10 $
b10 &
1#
#130000
0#
#135000
b0 +
b0 *
0!
0)
1'
b0 $
b0 &
1#
#140000
0#
#145000
1#
#150000
0#
#155000
b10 *
1)
0'
b10 $
b10 &
1#
#160000
0#
#165000
b10 +
b10 *
0)
1'
b0 $
b0 &
1#
#170000
0#
#175000
b11 *
1(
0'
b1 $
b1 &
1#
#180000
0#
#185000
b11 +
b11 *
0(
1'
b0 $
b0 &
1#
#190000
0#
#195000
b0 *
1"
1!
1)
0'
b10 $
b10 &
1#
#200000
0#
#205000
b0 +
b0 *
0"
0!
0)
1'
b0 $
b0 &
1#
