LAB2/problem2_traffic/traffic_light.v

module traffic_light(
    input  wire clk,
    input  wire rst,  
    input  wire tick,  
    output reg  ns_g,
    output reg  ns_y,
    output reg  ns_r,
    output reg  ew_g,
    output reg  ew_y,
    output reg  ew_r
);


localparam S_NS_G = 2'd0;
localparam S_NS_Y = 2'd1;
localparam S_EW_G = 2'd2;
localparam S_EW_Y = 2'd3;

reg [1:0] state, next_state;

reg [3:0] tick_cnt;


always @(*) begin
    next_state = state;
    case (state)
        S_NS_G: if (tick && tick_cnt == 4) next_state = S_NS_Y; 
        S_NS_Y: if (tick && tick_cnt == 1) next_state = S_EW_G; 
        S_EW_G: if (tick && tick_cnt == 4) next_state = S_EW_Y; 
        S_EW_Y: if (tick && tick_cnt == 1) next_state = S_NS_G; 
        default: next_state = S_NS_G;
    endcase
end

always @(posedge clk) begin
    if (rst) begin
        state    <= S_NS_G;
        tick_cnt <= 0;
    end else begin
        if (tick) begin
            if (next_state != state) begin
                state    <= next_state;
                tick_cnt <= 0;          
            end else begin
                tick_cnt <= tick_cnt + 1; 
            end
        end
        
    end
end

always @(*) begin
    ns_g = 0; ns_y = 0; ns_r = 0;
    ew_g = 0; ew_y = 0; ew_r = 0;

    case (state)
        S_NS_G: begin
            ns_g = 1;      
            ew_r = 1;     
        end
        S_NS_Y: begin
            ns_y = 1;     
            ew_r = 1;    
        end
        S_EW_G: begin
            ew_g = 1;     
            ns_r = 1;     
        end
        S_EW_Y: begin
            ew_y = 1;   
            ns_r = 1;    
        end
        default: begin
            ns_r = 1;
            ew_r = 1;
        end
    endcase
end

endmodule

LAB2/problem2_traffic/tb_traffic_light.v

`timescale 1ns/1ps

module tb_traffic_light;
    reg clk;
    reg rst;
    reg tick;
    wire ns_g, ns_y, ns_r, ew_g, ew_y, ew_r;

    
    traffic_light dut (
        .clk(clk), .rst(rst), .tick(tick),
        .ns_g(ns_g), .ns_y(ns_y), .ns_r(ns_r),
        .ew_g(ew_g), .ew_y(ew_y), .ew_r(ew_r)
    );

    
    initial begin
        clk = 0;
        forever #5 clk = ~clk;
    end

   
    initial begin
        $dumpfile("dump.vcd");
        $dumpvars(0, tb_traffic_light);

        rst = 1;
        tick = 0;
        #20;    
        rst = 0;

        #2000;
        $display("Testbench done.");
        $finish;
    end

    reg [2:0] fast_div;
    always @(posedge clk) begin
        if (rst) begin
            fast_div <= 0;
            tick <= 0;
        end else begin
            if (fast_div == 4) begin
                tick <= 1;
                fast_div <= 0;
            end else begin
                tick <= 0;
                fast_div <= fast_div + 1;
            end
        end
    end

    always @(posedge clk) begin
        if (tick) begin
            $display("%0t: tick -- ns_g=%b ns_y=%b ns_r=%b | ew_g=%b ew_y=%b ew_r=%b",
                     $time, ns_g, ns_y, ns_r, ew_g, ew_y, ew_r);
        end
    end

endmodule

LAB2/problem2_traffic/dump.vcd
$date
	Sun Aug 17 22:56:25 2025
$end
$version
	Icarus Verilog
$end
$timescale
	1ps
$end
$scope module tb_traffic_light $end
$var wire 1 ! ns_y $end
$var wire 1 " ns_r $end
$var wire 1 # ns_g $end
$var wire 1 $ ew_y $end
$var wire 1 % ew_r $end
$var wire 1 & ew_g $end
$var reg 1 ' clk $end
$var reg 3 ( fast_div [2:0] $end
$var reg 1 ) rst $end
$var reg 1 * tick $end
$scope module dut $end
$var wire 1 ' clk $end
$var wire 1 ) rst $end
$var wire 1 * tick $end
$var reg 1 & ew_g $end
$var reg 1 % ew_r $end
$var reg 1 $ ew_y $end
$var reg 2 + next_state [1:0] $end
$var reg 1 # ns_g $end
$var reg 1 " ns_r $end
$var reg 1 ! ns_y $end
$var reg 2 , state [1:0] $end
$var reg 4 - tick_cnt [3:0] $end
$upscope $end
$upscope $end
$enddefinitions $end
#0
$dumpvars
bx -
bx ,
b0 +
0*
1)
bx (
0'
x&
x%
x$
x#
x"
x!
$end
#5000
1%
0$
0&
0"
0!
1#
b0 -
b0 ,
b0 (
1'
#10000
0'
#15000
1'
#20000
0'
0)
#25000
b1 (
1'
#30000
0'
#35000
b10 (
1'
#40000
0'
#45000
b11 (
1'
#50000
0'
#55000
b100 (
1'
#60000
0'
#65000
b0 (
1*
1'
#70000
0'
#75000
b1 (
0*
b1 -
1'
#80000
0'
#85000
b10 (
1'
#90000
0'
#95000
b11 (
1'
#100000
0'
#105000
b100 (
1'
#110000
0'
#115000
b0 (
1*
1'
#120000
0'
#125000
b10 -
b1 (
0*
1'
#130000
0'
#135000
b10 (
1'
#140000
0'
#145000
b11 (
1'
#150000
0'
#155000
b100 (
1'
#160000
0'
#165000
b0 (
1*
1'
#170000
0'
#175000
b1 (
0*
b11 -
1'
#180000
0'
#185000
b10 (
1'
#190000
0'
#195000
b11 (
1'
#200000
0'
#205000
b100 (
1'
#210000
0'
#215000
b0 (
1*
1'
#220000
0'
#225000
b100 -
b1 (
0*
1'
#230000
0'
#235000
b10 (
1'
#240000
0'
#245000
b11 (
1'
#250000
0'
#255000
b100 (
1'
#260000
0'
#265000
b1 +
b0 (
1*
1'
#270000
0'
#275000
1!
1%
0#
b1 (
0*
b0 -
b1 ,
1'
#280000
0'
#285000
b10 (
1'
#290000
0'
#295000
b11 (
1'
#300000
0'
#305000
b100 (
1'
#310000
0'
#315000
b0 (
1*
1'
#320000
0'
#325000
b1 -
b1 (
0*
1'
#330000
0'
#335000
b10 (
1'
#340000
0'
#345000
b11 (
1'
#350000
0'
#355000
b100 (
1'
#360000
0'
#365000
b10 +
b0 (
1*
1'
#370000
0'
#375000
1"
1&
0%
0!
b1 (
0*
b0 -
b10 ,
1'
#380000
0'
#385000
b10 (
1'
#390000
0'
#395000
b11 (
1'
#400000
0'
#405000
b100 (
1'
#410000
0'
#415000
b0 (
1*
1'
#420000
0'
#425000
b1 -
b1 (
0*
1'
#430000
0'
#435000
b10 (
1'
#440000
0'
#445000
b11 (
1'
#450000
0'
#455000
b100 (
1'
#460000
0'
#465000
b0 (
1*
1'
#470000
0'
#475000
b1 (
0*
b10 -
1'
#480000
0'
#485000
b10 (
1'
#490000
0'
#495000
b11 (
1'
#500000
0'
#505000
b100 (
1'
#510000
0'
#515000
b0 (
1*
1'
#520000
0'
#525000
b11 -
b1 (
0*
1'
#530000
0'
#535000
b10 (
1'
#540000
0'
#545000
b11 (
1'
#550000
0'
#555000
b100 (
1'
#560000
0'
#565000
b0 (
1*
1'
#570000
0'
#575000
b1 (
0*
b100 -
1'
#580000
0'
#585000
b10 (
1'
#590000
0'
#595000
b11 (
1'
#600000
0'
#605000
b100 (
1'
#610000
0'
#615000
b11 +
b0 (
1*
1'
#620000
0'
#625000
1$
0&
1"
b0 -
b11 ,
b1 (
0*
1'
#630000
0'
#635000
b10 (
1'
#640000
0'
#645000
b11 (
1'
#650000
0'
#655000
b100 (
1'
#660000
0'
#665000
b0 (
1*
1'
#670000
0'
#675000
b1 (
0*
b1 -
1'
#680000
0'
#685000
b10 (
1'
#690000
0'
#695000
b11 (
1'
#700000
0'
#705000
b100 (
1'
#710000
0'
#715000
b0 +
b0 (
1*
1'
#720000
0'
#725000
1%
1#
0$
0"
b0 -
b0 ,
b1 (
0*
1'
#730000
0'
#735000
b10 (
1'
#740000
0'
#745000
b11 (
1'
#750000
0'
#755000
b100 (
1'
#760000
0'
#765000
b0 (
1*
1'
#770000
0'
#775000
b1 (
0*
b1 -
1'
#780000
0'
#785000
b10 (
1'
#790000
0'
#795000
b11 (
1'
#800000
0'
#805000
b100 (
1'
#810000
0'
#815000
b0 (
1*
1'
#820000
0'
#825000
b10 -
b1 (
0*
1'
#830000
0'
#835000
b10 (
1'
#840000
0'
#845000
b11 (
1'
#850000
0'
#855000
b100 (
1'
#860000
0'
#865000
b0 (
1*
1'
#870000
0'
#875000
b1 (
0*
b11 -
1'
#880000
0'
#885000
b10 (
1'
#890000
0'
#895000
b11 (
1'
#900000
0'
#905000
b100 (
1'
#910000
0'
#915000
b0 (
1*
1'
#920000
0'
#925000
b100 -
b1 (
0*
1'
#930000
0'
#935000
b10 (
1'
#940000
0'
#945000
b11 (
1'
#950000
0'
#955000
b100 (
1'
#960000
0'
#965000
b1 +
b0 (
1*
1'
#970000
0'
#975000
1!
1%
0#
b1 (
0*
b0 -
b1 ,
1'
#980000
0'
#985000
b10 (
1'
#990000
0'
#995000
b11 (
1'
#1000000
0'
#1005000
b100 (
1'
#1010000
0'
#1015000
b0 (
1*
1'
#1020000
0'
#1025000
b1 -
b1 (
0*
1'
#1030000
0'
#1035000
b10 (
1'
#1040000
0'
#1045000
b11 (
1'
#1050000
0'
#1055000
b100 (
1'
#1060000
0'
#1065000
b10 +
b0 (
1*
1'
#1070000
0'
#1075000
1"
1&
0%
0!
b1 (
0*
b0 -
b10 ,
1'
#1080000
0'
#1085000
b10 (
1'
#1090000
0'
#1095000
b11 (
1'
#1100000
0'
#1105000
b100 (
1'
#1110000
0'
#1115000
b0 (
1*
1'
#1120000
0'
#1125000
b1 -
b1 (
0*
1'
#1130000
0'
#1135000
b10 (
1'
#1140000
0'
#1145000
b11 (
1'
#1150000
0'
#1155000
b100 (
1'
#1160000
0'
#1165000
b0 (
1*
1'
#1170000
0'
#1175000
b1 (
0*
b10 -
1'
#1180000
0'
#1185000
b10 (
1'
#1190000
0'
#1195000
b11 (
1'
#1200000
0'
#1205000
b100 (
1'
#1210000
0'
#1215000
b0 (
1*
1'
#1220000
0'
#1225000
b11 -
b1 (
0*
1'
#1230000
0'
#1235000
b10 (
1'
#1240000
0'
#1245000
b11 (
1'
#1250000
0'
#1255000
b100 (
1'
#1260000
0'
#1265000
b0 (
1*
1'
#1270000
0'
#1275000
b1 (
0*
b100 -
1'
#1280000
0'
#1285000
b10 (
1'
#1290000
0'
#1295000
b11 (
1'
#1300000
0'
#1305000
b100 (
1'
#1310000
0'
#1315000
b11 +
b0 (
1*
1'
#1320000
0'
#1325000
1$
0&
1"
b0 -
b11 ,
b1 (
0*
1'
#1330000
0'
#1335000
b10 (
1'
#1340000
0'
#1345000
b11 (
1'
#1350000
0'
#1355000
b100 (
1'
#1360000
0'
#1365000
b0 (
1*
1'
#1370000
0'
#1375000
b1 (
0*
b1 -
1'
#1380000
0'
#1385000
b10 (
1'
#1390000
0'
#1395000
b11 (
1'
#1400000
0'
#1405000
b100 (
1'
#1410000
0'
#1415000
b0 +
b0 (
1*
1'
#1420000
0'
#1425000
1%
1#
0$
0"
b0 -
b0 ,
b1 (
0*
1'
#1430000
0'
#1435000
b10 (
1'
#1440000
0'
#1445000
b11 (
1'
#1450000
0'
#1455000
b100 (
1'
#1460000
0'
#1465000
b0 (
1*
1'
#1470000
0'
#1475000
b1 (
0*
b1 -
1'
#1480000
0'
#1485000
b10 (
1'
#1490000
0'
#1495000
b11 (
1'
#1500000
0'
#1505000
b100 (
1'
#1510000
0'
#1515000
b0 (
1*
1'
#1520000
0'
#1525000
b10 -
b1 (
0*
1'
#1530000
0'
#1535000
b10 (
1'
#1540000
0'
#1545000
b11 (
1'
#1550000
0'
#1555000
b100 (
1'
#1560000
0'
#1565000
b0 (
1*
1'
#1570000
0'
#1575000
b1 (
0*
b11 -
1'
#1580000
0'
#1585000
b10 (
1'
#1590000
0'
#1595000
b11 (
1'
#1600000
0'
#1605000
b100 (
1'
#1610000
0'
#1615000
b0 (
1*
1'
#1620000
0'
#1625000
b100 -
b1 (
0*
1'
#1630000
0'
#1635000
b10 (
1'
#1640000
0'
#1645000
b11 (
1'
#1650000
0'
#1655000
b100 (
1'
#1660000
0'
#1665000
b1 +
b0 (
1*
1'
#1670000
0'
#1675000
1!
1%
0#
b1 (
0*
b0 -
b1 ,
1'
#1680000
0'
#1685000
b10 (
1'
#1690000
0'
#1695000
b11 (
1'
#1700000
0'
#1705000
b100 (
1'
#1710000
0'
#1715000
b0 (
1*
1'
#1720000
0'
#1725000
b1 -
b1 (
0*
1'
#1730000
0'
#1735000
b10 (
1'
#1740000
0'
#1745000
b11 (
1'
#1750000
0'
#1755000
b100 (
1'
#1760000
0'
#1765000
b10 +
b0 (
1*
1'
#1770000
0'
#1775000
1"
1&
0%
0!
b1 (
0*
b0 -
b10 ,
1'
#1780000
0'
#1785000
b10 (
1'
#1790000
0'
#1795000
b11 (
1'
#1800000
0'
#1805000
b100 (
1'
#1810000
0'
#1815000
b0 (
1*
1'
#1820000
0'
#1825000
b1 -
b1 (
0*
1'
#1830000
0'
#1835000
b10 (
1'
#1840000
0'
#1845000
b11 (
1'
#1850000
0'
#1855000
b100 (
1'
#1860000
0'
#1865000
b0 (
1*
1'
#1870000
0'
#1875000
b1 (
0*
b10 -
1'
#1880000
0'
#1885000
b10 (
1'
#1890000
0'
#1895000
b11 (
1'
#1900000
0'
#1905000
b100 (
1'
#1910000
0'
#1915000
b0 (
1*
1'
#1920000
0'
#1925000
b11 -
b1 (
0*
1'
#1930000
0'
#1935000
b10 (
1'
#1940000
0'
#1945000
b11 (
1'
#1950000
0'
#1955000
b100 (
1'
#1960000
0'
#1965000
b0 (
1*
1'
#1970000
0'
#1975000
b1 (
0*
b100 -
1'
#1980000
0'
#1985000
b10 (
1'
#1990000
0'
#1995000
b11 (
1'
#2000000
0'
#2005000
b100 (
1'
#2010000
0'
#2015000
b11 +
b0 (
1*
1'
