LAB2/problem1_seqdet/seq_detect_mealy.v
module seq_detect_mealy(
    input  wire clk,
    input  wire rst,   
    input  wire din,   
    output reg  y
);
    
    localparam S0=2'b00, S1=2'b01, S2=2'b10, S3=2'b11;
    reg [1:0] state, next_state;

    always @(posedge clk) begin
        if (rst) state <= S0;
        else     state <= next_state;
    end

    always @(*) begin
        y = 0;
        case (state)
            S0: next_state = din ? S1 : S0;
            S1: next_state = din ? S2 : S0;
            S2: next_state = din ? S2 : S3;
            S3: begin
                if (din) begin y = 1; next_state = S1; end
                else           next_state = S0;
            end
        endcase
    end
endmodule

LAB2/problem1_seqdet/tb_seq_detect_mealy.v
module tb_seq_detect_mealy;
  reg clk, rst, din;
  wire y;

  seq_detect_mealy dut(.clk(clk), .rst(rst), .din(din), .y(y));

  
  initial begin clk=0; forever #5 clk=~clk; end

  initial begin
    $dumpfile("waves/dump.vcd");  
    $dumpvars(0, tb_seq_detect_mealy); 
    rst = 1; din = 0; #20; rst = 0;
    din=1; #10; din=1; #10; din=0; #10; din=1; #10;
    din=1; #10; din=0; #10; din=1; #10; din=1; #10;
    din=1; #10; din=0; #10; din=1; #10;

    #20 $finish;
  end
endmodule

LAB2/problem1_seqdet/waves/dump.vcd
$date
	Sun Aug 17 22:06:05 2025
$end
$version
	Icarus Verilog
$end
$timescale
	1s
$end
$scope module tb_seq_detect_mealy $end
$var wire 1 ! y $end
$var reg 1 " clk $end
$var reg 1 # din $end
$var reg 1 $ rst $end
$scope module dut $end
$var wire 1 " clk $end
$var wire 1 # din $end
$var wire 1 $ rst $end
$var reg 2 % next_state [1:0] $end
$var reg 2 & state [1:0] $end
$var reg 1 ! y $end
$upscope $end
$upscope $end
$enddefinitions $end
#0
$dumpvars
bx &
bx %
1$
0#
0"
0!
$end
#5
b0 %
b0 &
1"
#10
0"
#15
1"
#20
b1 %
0"
1#
0$
#25
b10 %
b1 &
1"
#30
0"
#35
b10 &
1"
#40
b11 %
0"
0#
#45
b0 %
b11 &
1"
#50
b1 %
1!
0"
1#
#55
b10 %
0!
b1 &
1"
#60
0"
#65
b10 &
1"
#70
b11 %
0"
0#
#75
b0 %
b11 &
1"
#80
b1 %
1!
0"
1#
#85
b10 %
0!
b1 &
1"
#90
0"
#95
b10 &
1"
#100
0"
#105
1"
#110
b11 %
0"
0#
#115
b0 %
b11 &
1"
#120
b1 %
1!
0"
1#
#125
b10 %
0!
b1 &
1"
#130
0"
#135
b10 &
1"
